longchat/__init__.py
longchat/conversation.py
longchat/train/utils.py
longchat/train/fine_tune/train.py
longchat/train/fine_tune/train_condense_16K.py
longchat/train/fine_tune/train_flash.py
longchat/train/monkey_patch/llama_condense_monkey_patch.py
longchat/train/monkey_patch/llama_flash_attn_monkey_patch.py
longchat/train/monkey_patch/llama_xformer_monkey_patch.py
longchat/train/pretrain/pretrain.py
longchat/train/pretrain/pretrain_flash.py
longchat/train/pretrain/pretrain_xformer.py
longeval/auto_topic_eval.py
longeval/eval.py
longeval/generate_testcases.py
longeval/utils.py
longchat-0.1.0.dist-info/METADATA
longchat-0.1.0.dist-info/WHEEL
longchat-0.1.0.dist-info/top_level.txt
longchat-0.1.0.dist-info/RECORD
