Metadata-Version: 2.1
Name: longchat
Version: 0.1.0
Summary: LongChat and LongEval
Classifier: Programming Language :: Python :: 3
Classifier: License :: OSI Approved :: Apache Software License
Requires-Python: >=3.8
Requires-Dist: accelerate
Requires-Dist: fastapi
Requires-Dist: gradio
Requires-Dist: markdown2[all]
Requires-Dist: numpy
Requires-Dist: prompt-toolkit >=3.0.0
Requires-Dist: requests
Requires-Dist: rich >=10.0.0
Requires-Dist: sentencepiece
Requires-Dist: shortuuid
Requires-Dist: transformers >=4.28.0
Requires-Dist: tokenizers >=0.12.1
Requires-Dist: torch
Requires-Dist: uvicorn
Requires-Dist: wandb
Requires-Dist: httpx
Requires-Dist: pydantic
Requires-Dist: tiktoken
Requires-Dist: openai
Requires-Dist: fschat
Requires-Dist: cpm-kernels
Provides-Extra: dev
Requires-Dist: black ==23.3.0 ; extra == 'dev'
Requires-Dist: pylint ==2.8.2 ; extra == 'dev'
